[{"nodemeta": ["listing", "listing", "listing"], "stats": {"2018/11/19": {"listing": {"tag_listing": [1, 0]}}, "listing": {"rtag_listing": [], "rcreate_listing": [], "tag_listing": [["[1651, 29]", "2018/11/19", "2018/12/03"]], "create_listing": [["[95, 1651]", "2018/11/19", "2018/12/03"]]}}, "title": "small turkey", "cumu_totals": {"social": 0.0, "story": 0.0, "transaction": 0.0, "listing": 1.0}, "comment_listing": [], "create_listing": [["[95, 1651]", "2018/11/19", "2018/12/03"]], "kcore": 1, "edgetotals": {"transaction": 0, "story": 0, "social": 0, "listing": 2.0}, "tag_listing": [["[1651, 29]", "2018/11/19", "2018/12/03"]], "date": "2018/11/01", "avg_totals": {"social": 0.0, "story": 0.0, "transaction": 0.0, "listing": 4.0}, "label": "1651", "type": "listing", "spells": [["2018/11/19", "2018/12/03"]]}]