[{"kcore": 0, "stats": {}, "name": "food coop", "tag_story": [["[7320,7483]", "2017/10/30", "2017/10/30"]], "tags": [], "label": "tag_43", "cumu_totals": {"listing": 0, "story": 0, "transaction": 0, "social": 0}, "edgetotals": {"transaction": 0, "story": 0, "social": 0, "listing": 0}, "date": "2017/10/01", "avg_totals": {"listing": 0, "story": 0, "transaction": 0, "social": 0}, "nodemeta": ["story"], "type": "tag", "id": "43", "spells": [["2017/10/30", "2017/10/30"], ["2018/05/16", "2018/05/16"]]}, {"kcore": 0, "stats": {}, "name": "food coop", "tag_story": [["[7424,7483]", "2018/05/16", "2018/05/16"]], "tags": [], "label": "tag_43", "cumu_totals": {"listing": 0, "story": 0, "transaction": 0, "social": 0}, "edgetotals": {"transaction": 0, "story": 0, "social": 0, "listing": 0}, "date": "2018/05/01", "avg_totals": {"listing": 0, "story": 0, "transaction": 0, "social": 0}, "nodemeta": ["story"], "type": "tag", "id": "43", "spells": [["2017/10/30", "2017/10/30"], ["2018/05/16", "2018/05/16"]]}]